<countries><country><name>Austria</name><oboleli>89</oboleli><preminuli>4</preminuli><izleceni>37</izleceni></country><country><name>Serbia</name><oboleli>1423</oboleli><preminuli>54</preminuli><izleceni>45</izleceni></country><country><name>Croatia</name><oboleli>9000</oboleli><preminuli>34</preminuli><izleceni>500</izleceni></country><country><name>Hungary</name><oboleli>55</oboleli><preminuli>2</preminuli><izleceni>13</izleceni></country><country><name>Germany</name><oboleli>600</oboleli><preminuli>20</preminuli><izleceni>400</izleceni></country><country><name>Romania</name><oboleli>900</oboleli><preminuli>40</preminuli><izleceni>123</izleceni></country></countries>